pk_encryptor/__init__.py
pk_encryptor/utils/__init__.py
pk_encryptor/utils/arguments_parser.py
pk_encryptor/utils/data.py
pk_encryptor/utils/decryptor.py
pk_encryptor/utils/encryption_utils.py
pk_encryptor/utils/key_generator.py
pk_encryptor-0.0.6.dist-info/METADATA
pk_encryptor-0.0.6.dist-info/WHEEL
pk_encryptor-0.0.6.dist-info/top_level.txt
pk_encryptor-0.0.6.dist-info/RECORD
