Metadata-Version: 2.2
Name: pk_encryptor
Version: 0.0.6
Summary: pk_encryptor.
Author-email: Indeoo <indeooars@gmail.com>
License: MIT
Project-URL: Homepage, https://github.com/Indeoo/web3-wizzard-lib/
Requires-Python: >=3.7
Requires-Dist: cryptography==42.0.5
